gateway_outage_responder
