Metadata-Version: 1.1
Name: gateway-outage-responder
Version: 1.0.1
Summary: If it looks like the internet is out; do something!
Home-page: https://github.com/coddingtonbear/gateway-outage-responder
Author: Adam Coddington
Author-email: me@adamcoddington.net
License: UNKNOWN
Platform: UNKNOWN
Classifier: License :: OSI Approved :: MIT License
Classifier: Operating System :: OS Independent
Classifier: Programming Language :: Python :: 3
